{
  "diffEditor.ignoreTrimWhitespace": false,
  "editor.acceptSuggestionOnEnter": "off",
  "editor.formatOnSave": true,
  "editor.minimap.enabled": false,
  "editor.tabSize": 2,
  "git.autofetch": true,
  "git.confirmSync": false,
  "git.enableSmartCommit": true,
  "python.formatting.provider": "black",
  "terminal.integrated.fontFamily": "'FiraCode Nerd Font Mono', 'monospace', monospace",
  "workbench.colorTheme": "GitHub Dark High Contrast",
  "workbench.editor.enablePreview": false,
  "files.watcherExclude": {
    "**/.git/objects/**": true,
    "**/.git/subtree-cache/**": true
  },
  "yaml.customTags": [
    "!reference sequence"
  ],
  "[json]": {
    "editor.defaultFormatter": "vscode.json-language-features"
  },
  "[jsonc]": {
    "editor.defaultFormatter": "vscode.json-language-features"
  },
  "[markdown]": {
    "editor.defaultFormatter": "yzhang.markdown-all-in-one"
  },
  "[yaml]": {
    "editor.defaultFormatter": "redhat.vscode-yaml"
  },
  "[python]": {
    "editor.formatOnType": true
  },
}